roleml/__init__.py
roleml/features.py
roleml/roleml.py
roleml/data/__init__.py
roleml/data/constants.json
roleml/data/load_constants.py
roleml/data/role_identification_model_32bits.sav
roleml/data/role_identification_model_64bits.sav
roleml/data/role_identification_model_64bits_39.sav
roleml/exceptions/__init__.py
roleml/exceptions/exceptions.py
roleml-0.2.3.dist-info/LICENSE
roleml-0.2.3.dist-info/METADATA
roleml-0.2.3.dist-info/WHEEL
roleml-0.2.3.dist-info/top_level.txt
roleml-0.2.3.dist-info/RECORD
