Metadata-Version: 2.1
Name: roleml
Version: 0.2.3
Summary: ML classifier for role in Riot API LoL matches
Home-page: https://github.com/Canisback/roleML
Author: Canisback
Author-email: canisback@gmail.com
License: UNKNOWN
Keywords: Riot API,python,machine learning,role,League of Legends, classifier
Platform: UNKNOWN
